scrapy_sentry_errors/__init__.py
scrapy_sentry_errors/extensions.py
scrapy_sentry_errors-1.0.0.dist-info/LICENSE
scrapy_sentry_errors-1.0.0.dist-info/METADATA
scrapy_sentry_errors-1.0.0.dist-info/WHEEL
scrapy_sentry_errors-1.0.0.dist-info/top_level.txt
scrapy_sentry_errors-1.0.0.dist-info/RECORD
